{
  "node": {
    "601f435e1ee906932885a36b02b1480071685e0cc2": {
      "workers": {
        "app/[[...slug]]/page": {
          "moduleId": 838458,
          "async": true,
          "exportedName": "signInAction",
          "filename": "src/app/actions/auth.ts"
        }
      },
      "layer": {
        "app/[[...slug]]/page": "action-browser"
      },
      "exportedName": "signInAction",
      "filename": "src/app/actions/auth.ts"
    },
    "4085da50dd0bf206cb5893edda258b1fb6087fb94b": {
      "workers": {
        "app/[[...slug]]/page": {
          "moduleId": 838458,
          "async": true,
          "exportedName": "signUpAction",
          "filename": "src/app/actions/auth.ts"
        }
      },
      "layer": {
        "app/[[...slug]]/page": "action-browser"
      },
      "exportedName": "signUpAction",
      "filename": "src/app/actions/auth.ts"
    },
    "606359dfb6b88f4f4b756b5c416007efbe2fcb1fcc": {
      "workers": {
        "app/[[...slug]]/page": {
          "moduleId": 838458,
          "async": true,
          "exportedName": "setBusinessPasswordAction",
          "filename": "src/app/actions/business.ts"
        }
      },
      "layer": {
        "app/[[...slug]]/page": "action-browser"
      },
      "exportedName": "setBusinessPasswordAction",
      "filename": "src/app/actions/business.ts"
    },
    "60364422a73402f3b5e59fb0aa7bbc8b9374b14ab5": {
      "workers": {
        "app/[[...slug]]/page": {
          "moduleId": 838458,
          "async": true,
          "exportedName": "verifyBusinessPasswordAction",
          "filename": "src/app/actions/business.ts"
        }
      },
      "layer": {
        "app/[[...slug]]/page": "action-browser"
      },
      "exportedName": "verifyBusinessPasswordAction",
      "filename": "src/app/actions/business.ts"
    },
    "408ffa5a6991ba3e64aa45862bed880555b1e6c2ac": {
      "workers": {
        "app/[[...slug]]/page": {
          "moduleId": 838458,
          "async": true,
          "exportedName": "removeBusinessPasswordAction",
          "filename": "src/app/actions/business.ts"
        }
      },
      "layer": {
        "app/[[...slug]]/page": "action-browser"
      },
      "exportedName": "removeBusinessPasswordAction",
      "filename": "src/app/actions/business.ts"
    },
    "4097618b1feff5bb1f466d7ef73901ab8f5cb1ab7d": {
      "workers": {
        "app/[[...slug]]/page": {
          "moduleId": 838458,
          "async": true,
          "exportedName": "getBusinessLocationsAction",
          "filename": "src/app/actions/business.ts"
        }
      },
      "layer": {
        "app/[[...slug]]/page": "action-browser"
      },
      "exportedName": "getBusinessLocationsAction",
      "filename": "src/app/actions/business.ts"
    },
    "60d7c3d2a9fae9e08d24867d93fe36b7505e38a2e0": {
      "workers": {
        "app/[[...slug]]/page": {
          "moduleId": 838458,
          "async": true,
          "exportedName": "createBusinessAction",
          "filename": "src/app/actions/business.ts"
        }
      },
      "layer": {
        "app/[[...slug]]/page": "action-browser"
      },
      "exportedName": "createBusinessAction",
      "filename": "src/app/actions/business.ts"
    },
    "70dd23d5987603253209c3c012d3079124803d1be2": {
      "workers": {
        "app/[[...slug]]/page": {
          "moduleId": 838458,
          "async": true,
          "exportedName": "updateBusinessAction",
          "filename": "src/app/actions/business.ts"
        }
      },
      "layer": {
        "app/[[...slug]]/page": "action-browser"
      },
      "exportedName": "updateBusinessAction",
      "filename": "src/app/actions/business.ts"
    },
    "600c0285b1a230950447aea12ad4361b35b7957acf": {
      "workers": {
        "app/[[...slug]]/page": {
          "moduleId": 838458,
          "async": true,
          "exportedName": "deleteBusinessAction",
          "filename": "src/app/actions/business.ts"
        }
      },
      "layer": {
        "app/[[...slug]]/page": "action-browser"
      },
      "exportedName": "deleteBusinessAction",
      "filename": "src/app/actions/business.ts"
    },
    "60b753a09691b4217e6751307f35f59cee17dc35d7": {
      "workers": {
        "app/[[...slug]]/page": {
          "moduleId": 838458,
          "async": true,
          "exportedName": "resetBusinessAction",
          "filename": "src/app/actions/business.ts"
        }
      },
      "layer": {
        "app/[[...slug]]/page": "action-browser"
      },
      "exportedName": "resetBusinessAction",
      "filename": "src/app/actions/business.ts"
    },
    "4071ca673ee83cf4e327275e6cacdae94950b7fa0e": {
      "workers": {
        "app/[[...slug]]/page": {
          "moduleId": 838458,
          "async": true,
          "exportedName": "getProfilesAction",
          "filename": "src/app/actions/profiles.ts"
        }
      },
      "layer": {
        "app/[[...slug]]/page": "action-browser"
      },
      "exportedName": "getProfilesAction",
      "filename": "src/app/actions/profiles.ts"
    },
    "608339c001209003cae74bf0c032c55c8444c1ef85": {
      "workers": {
        "app/[[...slug]]/page": {
          "moduleId": 838458,
          "async": true,
          "exportedName": "createProfileAction",
          "filename": "src/app/actions/profiles.ts"
        }
      },
      "layer": {
        "app/[[...slug]]/page": "action-browser"
      },
      "exportedName": "createProfileAction",
      "filename": "src/app/actions/profiles.ts"
    },
    "6028252923753001f049a6422f229f06bbec8b1f79": {
      "workers": {
        "app/[[...slug]]/page": {
          "moduleId": 838458,
          "async": true,
          "exportedName": "updateProfileAction",
          "filename": "src/app/actions/profiles.ts"
        }
      },
      "layer": {
        "app/[[...slug]]/page": "action-browser"
      },
      "exportedName": "updateProfileAction",
      "filename": "src/app/actions/profiles.ts"
    },
    "40a4b8447ff959c91ed080f8a56d7de9480694b288": {
      "workers": {
        "app/[[...slug]]/page": {
          "moduleId": 838458,
          "async": true,
          "exportedName": "deleteProfileAction",
          "filename": "src/app/actions/profiles.ts"
        }
      },
      "layer": {
        "app/[[...slug]]/page": "action-browser"
      },
      "exportedName": "deleteProfileAction",
      "filename": "src/app/actions/profiles.ts"
    },
    "40ee1dba433f3b3dc0f2791052194d1420c0946197": {
      "workers": {
        "app/[[...slug]]/page": {
          "moduleId": 838458,
          "async": true,
          "exportedName": "getOnboardingStatusAction",
          "filename": "src/app/actions/business-settings.ts"
        }
      },
      "layer": {
        "app/[[...slug]]/page": "action-browser"
      },
      "exportedName": "getOnboardingStatusAction",
      "filename": "src/app/actions/business-settings.ts"
    },
    "4011d3f24165a1ff4c6519d47357cf1974ec9d298f": {
      "workers": {
        "app/[[...slug]]/page": {
          "moduleId": 838458,
          "async": true,
          "exportedName": "getAccountStatusAction",
          "filename": "src/app/actions/business-settings.ts"
        }
      },
      "layer": {
        "app/[[...slug]]/page": "action-browser"
      },
      "exportedName": "getAccountStatusAction",
      "filename": "src/app/actions/business-settings.ts"
    },
    "70837cf9b9b85e45a6367e7e3a592457c34a990d2e": {
      "workers": {
        "app/[[...slug]]/page": {
          "moduleId": 838458,
          "async": true,
          "exportedName": "upsertBusinessSettingsAction",
          "filename": "src/app/actions/business-settings.ts"
        }
      },
      "layer": {
        "app/[[...slug]]/page": "action-browser"
      },
      "exportedName": "upsertBusinessSettingsAction",
      "filename": "src/app/actions/business-settings.ts"
    },
    "40290a4fc6b8571a026afeb877566edb807919e482": {
      "workers": {
        "app/[[...slug]]/page": {
          "moduleId": 838458,
          "async": true,
          "exportedName": "getBusinessSettingsAction",
          "filename": "src/app/actions/business-settings.ts"
        }
      },
      "layer": {
        "app/[[...slug]]/page": "action-browser"
      },
      "exportedName": "getBusinessSettingsAction",
      "filename": "src/app/actions/business-settings.ts"
    },
    "401d907b5cd7e0b2f207e9b555ac4fe2e14de08444": {
      "workers": {
        "app/[[...slug]]/page": {
          "moduleId": 838458,
          "async": true,
          "exportedName": "logActivityAction",
          "filename": "src/app/actions/activity.ts"
        }
      },
      "layer": {
        "app/[[...slug]]/page": "action-browser"
      },
      "exportedName": "logActivityAction",
      "filename": "src/app/actions/activity.ts"
    },
    "703e9376bfaf2adbf9aba886e70ba6b561f6bf5e0c": {
      "workers": {
        "app/[[...slug]]/page": {
          "moduleId": 838458,
          "async": true,
          "exportedName": "getSalesAction",
          "filename": "src/app/actions/sales.ts"
        }
      },
      "layer": {
        "app/[[...slug]]/page": "action-browser"
      },
      "exportedName": "getSalesAction",
      "filename": "src/app/actions/sales.ts"
    },
    "40d9064371ce5c0811194879498fdc849fbf872b8a": {
      "workers": {
        "app/[[...slug]]/page": {
          "moduleId": 838458,
          "async": true,
          "exportedName": "deleteSaleAction",
          "filename": "src/app/actions/sales.ts"
        }
      },
      "layer": {
        "app/[[...slug]]/page": "action-browser"
      },
      "exportedName": "deleteSaleAction",
      "filename": "src/app/actions/sales.ts"
    },
    "70efb1cbb8fb1ba0a6880484e122dc6526ca64a0a4": {
      "workers": {
        "app/[[...slug]]/page": {
          "moduleId": 838458,
          "async": true,
          "exportedName": "getTotalExpensesAction",
          "filename": "src/app/actions/analytics.ts"
        }
      },
      "layer": {
        "app/[[...slug]]/page": "action-browser"
      },
      "exportedName": "getTotalExpensesAction",
      "filename": "src/app/actions/analytics.ts"
    },
    "7032a29d28bd01f4196de49c5bc81b9c93747c2fef": {
      "workers": {
        "app/[[...slug]]/page": {
          "moduleId": 838458,
          "async": true,
          "exportedName": "getExpensesForChartAction",
          "filename": "src/app/actions/expenses.ts"
        }
      },
      "layer": {
        "app/[[...slug]]/page": "action-browser"
      },
      "exportedName": "getExpensesForChartAction",
      "filename": "src/app/actions/expenses.ts"
    },
    "40d192c7133b72d6eb22105e9bdccca4dd09d6c312": {
      "workers": {
        "app/[[...slug]]/page": {
          "moduleId": 838458,
          "async": true,
          "exportedName": "getSalesCategoriesAction",
          "filename": "src/app/actions/sales.ts"
        }
      },
      "layer": {
        "app/[[...slug]]/page": "action-browser"
      },
      "exportedName": "getSalesCategoriesAction",
      "filename": "src/app/actions/sales.ts"
    },
    "78f34606537592502556e5eff8bf435c75821848df": {
      "workers": {
        "app/[[...slug]]/page": {
          "moduleId": 838458,
          "async": true,
          "exportedName": "createSalesCategoryAction",
          "filename": "src/app/actions/sales.ts"
        }
      },
      "layer": {
        "app/[[...slug]]/page": "action-browser"
      },
      "exportedName": "createSalesCategoryAction",
      "filename": "src/app/actions/sales.ts"
    },
    "601c76a41759792ff7ede8d55df9ffa468b0da22c2": {
      "workers": {
        "app/[[...slug]]/page": {
          "moduleId": 838458,
          "async": true,
          "exportedName": "updateSalesCategoryAction",
          "filename": "src/app/actions/sales.ts"
        }
      },
      "layer": {
        "app/[[...slug]]/page": "action-browser"
      },
      "exportedName": "updateSalesCategoryAction",
      "filename": "src/app/actions/sales.ts"
    },
    "4048df543ea89e6b499e78c5496b2ff9ac8b3367ff": {
      "workers": {
        "app/[[...slug]]/page": {
          "moduleId": 838458,
          "async": true,
          "exportedName": "deleteSalesCategoryAction",
          "filename": "src/app/actions/sales.ts"
        }
      },
      "layer": {
        "app/[[...slug]]/page": "action-browser"
      },
      "exportedName": "deleteSalesCategoryAction",
      "filename": "src/app/actions/sales.ts"
    },
    "408055c65091de6e86656304d04a002881aed3acc6": {
      "workers": {
        "app/[[...slug]]/page": {
          "moduleId": 838458,
          "async": true,
          "exportedName": "getCashAccountsAction",
          "filename": "src/app/actions/finance.ts"
        }
      },
      "layer": {
        "app/[[...slug]]/page": "action-browser"
      },
      "exportedName": "getCashAccountsAction",
      "filename": "src/app/actions/finance.ts"
    },
    "40fec0c16d5b967e0b7b13b4f39e9f33caa55d98fd": {
      "workers": {
        "app/[[...slug]]/page": {
          "moduleId": 838458,
          "async": true,
          "exportedName": "createCashAccountAction",
          "filename": "src/app/actions/finance.ts"
        }
      },
      "layer": {
        "app/[[...slug]]/page": "action-browser"
      },
      "exportedName": "createCashAccountAction",
      "filename": "src/app/actions/finance.ts"
    },
    "60cff6e1bde4cdde91ed3aaa29411ed65f1ac6b8ba": {
      "workers": {
        "app/[[...slug]]/page": {
          "moduleId": 838458,
          "async": true,
          "exportedName": "updateCashAccountAction",
          "filename": "src/app/actions/finance.ts"
        }
      },
      "layer": {
        "app/[[...slug]]/page": "action-browser"
      },
      "exportedName": "updateCashAccountAction",
      "filename": "src/app/actions/finance.ts"
    },
    "609fff12b333f8481f6eaa00c9f6ed0ca7485d5f62": {
      "workers": {
        "app/[[...slug]]/page": {
          "moduleId": 838458,
          "async": true,
          "exportedName": "deleteCashAccountAction",
          "filename": "src/app/actions/finance.ts"
        }
      },
      "layer": {
        "app/[[...slug]]/page": "action-browser"
      },
      "exportedName": "deleteCashAccountAction",
      "filename": "src/app/actions/finance.ts"
    },
    "701a700c12f80accdeeab232d537f79439d8fe9e50": {
      "workers": {
        "app/[[...slug]]/page": {
          "moduleId": 838458,
          "async": true,
          "exportedName": "deleteCashAccountWithTransactionsAction",
          "filename": "src/app/actions/finance.ts"
        }
      },
      "layer": {
        "app/[[...slug]]/page": "action-browser"
      },
      "exportedName": "deleteCashAccountWithTransactionsAction",
      "filename": "src/app/actions/finance.ts"
    },
    "60a22285198ef838d83b1b4a602809518cbd22267e": {
      "workers": {
        "app/[[...slug]]/page": {
          "moduleId": 838458,
          "async": true,
          "exportedName": "getCashAccountBalanceAction",
          "filename": "src/app/actions/finance.ts"
        }
      },
      "layer": {
        "app/[[...slug]]/page": "action-browser"
      },
      "exportedName": "getCashAccountBalanceAction",
      "filename": "src/app/actions/finance.ts"
    },
    "6050d5e4425dec9de12384682af8632685a43503f6": {
      "workers": {
        "app/[[...slug]]/page": {
          "moduleId": 838458,
          "async": true,
          "exportedName": "getCashTransactionsAction",
          "filename": "src/app/actions/finance.ts"
        }
      },
      "layer": {
        "app/[[...slug]]/page": "action-browser"
      },
      "exportedName": "getCashTransactionsAction",
      "filename": "src/app/actions/finance.ts"
    },
    "4064724fc471e698ee76d294a980e2a65c0a9c856a": {
      "workers": {
        "app/[[...slug]]/page": {
          "moduleId": 838458,
          "async": true,
          "exportedName": "createCashTransactionAction",
          "filename": "src/app/actions/finance.ts"
        }
      },
      "layer": {
        "app/[[...slug]]/page": "action-browser"
      },
      "exportedName": "createCashTransactionAction",
      "filename": "src/app/actions/finance.ts"
    },
    "60e4c60d7aa378a229209542057eb77c66409f1850": {
      "workers": {
        "app/[[...slug]]/page": {
          "moduleId": 838458,
          "async": true,
          "exportedName": "updateCashTransactionAction",
          "filename": "src/app/actions/finance.ts"
        }
      },
      "layer": {
        "app/[[...slug]]/page": "action-browser"
      },
      "exportedName": "updateCashTransactionAction",
      "filename": "src/app/actions/finance.ts"
    },
    "605e333b82184dfc91eaa2d1fe6090163e41e2aa78": {
      "workers": {
        "app/[[...slug]]/page": {
          "moduleId": 838458,
          "async": true,
          "exportedName": "deleteCashTransactionAction",
          "filename": "src/app/actions/finance.ts"
        }
      },
      "layer": {
        "app/[[...slug]]/page": "action-browser"
      },
      "exportedName": "deleteCashTransactionAction",
      "filename": "src/app/actions/finance.ts"
    },
    "60233cf66a8bd607780138afb600e5b4300ab3ce36": {
      "workers": {
        "app/[[...slug]]/page": {
          "moduleId": 838458,
          "async": true,
          "exportedName": "getAccountOpeningBalanceAction",
          "filename": "src/app/actions/finance.ts"
        }
      },
      "layer": {
        "app/[[...slug]]/page": "action-browser"
      },
      "exportedName": "getAccountOpeningBalanceAction",
      "filename": "src/app/actions/finance.ts"
    },
    "402f81bafe02611b5b5687b2b85c12e36ea9604ccf": {
      "workers": {
        "app/[[...slug]]/page": {
          "moduleId": 838458,
          "async": true,
          "exportedName": "createBulkCashTransactionsAction",
          "filename": "src/app/actions/finance.ts"
        }
      },
      "layer": {
        "app/[[...slug]]/page": "action-browser"
      },
      "exportedName": "createBulkCashTransactionsAction",
      "filename": "src/app/actions/finance.ts"
    },
    "40786257b46b845f51e5b90ff2502c389af049cc70": {
      "workers": {
        "app/[[...slug]]/page": {
          "moduleId": 838458,
          "async": true,
          "exportedName": "getInstallmentPaymentsAction",
          "filename": "src/app/actions/finance.ts"
        }
      },
      "layer": {
        "app/[[...slug]]/page": "action-browser"
      },
      "exportedName": "getInstallmentPaymentsAction",
      "filename": "src/app/actions/finance.ts"
    },
    "40112c882b84370baebfbdd88b55390cbebe0d524d": {
      "workers": {
        "app/[[...slug]]/page": {
          "moduleId": 838458,
          "async": true,
          "exportedName": "createInstallmentPaymentAction",
          "filename": "src/app/actions/finance.ts"
        }
      },
      "layer": {
        "app/[[...slug]]/page": "action-browser"
      },
      "exportedName": "createInstallmentPaymentAction",
      "filename": "src/app/actions/finance.ts"
    },
    "6021a6dd25147899fbda211078cd44cca985d89362": {
      "workers": {
        "app/[[...slug]]/page": {
          "moduleId": 838458,
          "async": true,
          "exportedName": "updateInstallmentPaymentAction",
          "filename": "src/app/actions/finance.ts"
        }
      },
      "layer": {
        "app/[[...slug]]/page": "action-browser"
      },
      "exportedName": "updateInstallmentPaymentAction",
      "filename": "src/app/actions/finance.ts"
    },
    "409394b83f001d081510671555a3855b10e38d2c72": {
      "workers": {
        "app/[[...slug]]/page": {
          "moduleId": 838458,
          "async": true,
          "exportedName": "deleteInstallmentPaymentAction",
          "filename": "src/app/actions/finance.ts"
        }
      },
      "layer": {
        "app/[[...slug]]/page": "action-browser"
      },
      "exportedName": "deleteInstallmentPaymentAction",
      "filename": "src/app/actions/finance.ts"
    },
    "78ab6573748e58002b49a105ac9332c6ce6438d0d6": {
      "workers": {
        "app/[[...slug]]/page": {
          "moduleId": 838458,
          "async": true,
          "exportedName": "linkInstallmentToCashAction",
          "filename": "src/app/actions/finance.ts"
        }
      },
      "layer": {
        "app/[[...slug]]/page": "action-browser"
      },
      "exportedName": "linkInstallmentToCashAction",
      "filename": "src/app/actions/finance.ts"
    },
    "4001af3a742114ad88aa5fa65b77c9b0daf7714c0e": {
      "workers": {
        "app/[[...slug]]/page": {
          "moduleId": 838458,
          "async": true,
          "exportedName": "unlinkInstallmentFromCashAction",
          "filename": "src/app/actions/finance.ts"
        }
      },
      "layer": {
        "app/[[...slug]]/page": "action-browser"
      },
      "exportedName": "unlinkInstallmentFromCashAction",
      "filename": "src/app/actions/finance.ts"
    },
    "7c50216f90d367a7092d0edb6ffc217f655b260170": {
      "workers": {
        "app/[[...slug]]/page": {
          "moduleId": 838458,
          "async": true,
          "exportedName": "getActivityHistoryAction",
          "filename": "src/app/actions/activity.ts"
        }
      },
      "layer": {
        "app/[[...slug]]/page": "action-browser"
      },
      "exportedName": "getActivityHistoryAction",
      "filename": "src/app/actions/activity.ts"
    },
    "40227d1c2ed5cbf6324cf519682235031f0a3138a5": {
      "workers": {
        "app/[[...slug]]/page": {
          "moduleId": 838458,
          "async": true,
          "exportedName": "getCustomersAction",
          "filename": "src/app/actions/customers.ts"
        }
      },
      "layer": {
        "app/[[...slug]]/page": "action-browser"
      },
      "exportedName": "getCustomersAction",
      "filename": "src/app/actions/customers.ts"
    },
    "708938753470d59bd6fa4ddf41a8a3581263dd393b": {
      "workers": {
        "app/[[...slug]]/page": {
          "moduleId": 838458,
          "async": true,
          "exportedName": "createCustomerAction",
          "filename": "src/app/actions/customers.ts"
        }
      },
      "layer": {
        "app/[[...slug]]/page": "action-browser"
      },
      "exportedName": "createCustomerAction",
      "filename": "src/app/actions/customers.ts"
    },
    "609ad415d8b556837c750a19320a30ea6d4beaf896": {
      "workers": {
        "app/[[...slug]]/page": {
          "moduleId": 838458,
          "async": true,
          "exportedName": "updateCustomerAction",
          "filename": "src/app/actions/customers.ts"
        }
      },
      "layer": {
        "app/[[...slug]]/page": "action-browser"
      },
      "exportedName": "updateCustomerAction",
      "filename": "src/app/actions/customers.ts"
    },
    "40f9d32b0ea15e5c8f0b3441eec79ddb30815f1c83": {
      "workers": {
        "app/[[...slug]]/page": {
          "moduleId": 838458,
          "async": true,
          "exportedName": "deleteCustomerAction",
          "filename": "src/app/actions/customers.ts"
        }
      },
      "layer": {
        "app/[[...slug]]/page": "action-browser"
      },
      "exportedName": "deleteCustomerAction",
      "filename": "src/app/actions/customers.ts"
    },
    "602de18dc3faf52666fcf9224768f7ac9c1a6340ca": {
      "workers": {
        "app/[[...slug]]/page": {
          "moduleId": 838458,
          "async": true,
          "exportedName": "getCustomerByNameAction",
          "filename": "src/app/actions/sales.ts"
        }
      },
      "layer": {
        "app/[[...slug]]/page": "action-browser"
      },
      "exportedName": "getCustomerByNameAction",
      "filename": "src/app/actions/sales.ts"
    },
    "601a24df33adeed822b4de1bc4a7ea1dad51e405a6": {
      "workers": {
        "app/[[...slug]]/page": {
          "moduleId": 838458,
          "async": true,
          "exportedName": "updateSaleCustomerAction",
          "filename": "src/app/actions/sales.ts"
        }
      },
      "layer": {
        "app/[[...slug]]/page": "action-browser"
      },
      "exportedName": "updateSaleCustomerAction",
      "filename": "src/app/actions/sales.ts"
    },
    "6055d418bbb34217108fb09f6c6e07a1977765bffb": {
      "workers": {
        "app/[[...slug]]/page": {
          "moduleId": 838458,
          "async": true,
          "exportedName": "getStockHistoryAction",
          "filename": "src/app/actions/inventory.ts"
        }
      },
      "layer": {
        "app/[[...slug]]/page": "action-browser"
      },
      "exportedName": "getStockHistoryAction",
      "filename": "src/app/actions/inventory.ts"
    },
    "40193ce83d40b7dbf7c2991866f6d090da71bf2f59": {
      "workers": {
        "app/[[...slug]]/page": {
          "moduleId": 838458,
          "async": true,
          "exportedName": "createStockHistoryAction",
          "filename": "src/app/actions/inventory.ts"
        }
      },
      "layer": {
        "app/[[...slug]]/page": "action-browser"
      },
      "exportedName": "createStockHistoryAction",
      "filename": "src/app/actions/inventory.ts"
    },
    "60b4fb287dfbc2b628cca363587f00d76a36f3623b": {
      "workers": {
        "app/[[...slug]]/page": {
          "moduleId": 838458,
          "async": true,
          "exportedName": "recalculateStockChainAction",
          "filename": "src/app/actions/inventory.ts"
        }
      },
      "layer": {
        "app/[[...slug]]/page": "action-browser"
      },
      "exportedName": "recalculateStockChainAction",
      "filename": "src/app/actions/inventory.ts"
    },
    "60428e59105c2448bb202e52e31bf2d4492d8468f7": {
      "workers": {
        "app/[[...slug]]/page": {
          "moduleId": 838458,
          "async": true,
          "exportedName": "deleteStockHistoryEntriesByReferenceAction",
          "filename": "src/app/actions/inventory.ts"
        }
      },
      "layer": {
        "app/[[...slug]]/page": "action-browser"
      },
      "exportedName": "deleteStockHistoryEntriesByReferenceAction",
      "filename": "src/app/actions/inventory.ts"
    },
    "70e0c90d8c965637b3ae61b1f0dd8fc9a41ea083d6": {
      "workers": {
        "app/[[...slug]]/page": {
          "moduleId": 838458,
          "async": true,
          "exportedName": "updateStockHistoryDatesByReferenceAction",
          "filename": "src/app/actions/inventory.ts"
        }
      },
      "layer": {
        "app/[[...slug]]/page": "action-browser"
      },
      "exportedName": "updateStockHistoryDatesByReferenceAction",
      "filename": "src/app/actions/inventory.ts"
    },
    "60048cacdf8f6ab02d12e637338fb3a82838e3ab18": {
      "workers": {
        "app/[[...slug]]/page": {
          "moduleId": 838458,
          "async": true,
          "exportedName": "getRequisitionsAction",
          "filename": "src/app/actions/inventory.ts"
        }
      },
      "layer": {
        "app/[[...slug]]/page": "action-browser"
      },
      "exportedName": "getRequisitionsAction",
      "filename": "src/app/actions/inventory.ts"
    },
    "40e343dbe89cc3fb8304b10c9c62480d17ad426333": {
      "workers": {
        "app/[[...slug]]/page": {
          "moduleId": 838458,
          "async": true,
          "exportedName": "createRequisitionAction",
          "filename": "src/app/actions/inventory.ts"
        }
      },
      "layer": {
        "app/[[...slug]]/page": "action-browser"
      },
      "exportedName": "createRequisitionAction",
      "filename": "src/app/actions/inventory.ts"
    },
    "701e152aafbc4d4daee38965467b93e083a6e967b4": {
      "workers": {
        "app/[[...slug]]/page": {
          "moduleId": 838458,
          "async": true,
          "exportedName": "updateRequisitionAction",
          "filename": "src/app/actions/inventory.ts"
        }
      },
      "layer": {
        "app/[[...slug]]/page": "action-browser"
      },
      "exportedName": "updateRequisitionAction",
      "filename": "src/app/actions/inventory.ts"
    },
    "605622308fa711a2f7465dc0a63c7e00dbe7c0418e": {
      "workers": {
        "app/[[...slug]]/page": {
          "moduleId": 838458,
          "async": true,
          "exportedName": "deleteRequisitionAction",
          "filename": "src/app/actions/inventory.ts"
        }
      },
      "layer": {
        "app/[[...slug]]/page": "action-browser"
      },
      "exportedName": "deleteRequisitionAction",
      "filename": "src/app/actions/inventory.ts"
    },
    "7022b270c26116cc720c0fe09926fa8749c32b0ea9": {
      "workers": {
        "app/[[...slug]]/page": {
          "moduleId": 838458,
          "async": true,
          "exportedName": "getStockSummaryReportAction",
          "filename": "src/app/actions/inventory.ts"
        }
      },
      "layer": {
        "app/[[...slug]]/page": "action-browser"
      },
      "exportedName": "getStockSummaryReportAction",
      "filename": "src/app/actions/inventory.ts"
    },
    "605a5ac8c70aa01eb0dd29483cb3c24316ae309de0": {
      "workers": {
        "app/[[...slug]]/page": {
          "moduleId": 838458,
          "async": true,
          "exportedName": "getProductReconciliationAction",
          "filename": "src/app/actions/inventory.ts"
        }
      },
      "layer": {
        "app/[[...slug]]/page": "action-browser"
      },
      "exportedName": "getProductReconciliationAction",
      "filename": "src/app/actions/inventory.ts"
    },
    "406e0d925bc965618c40bddb0b2011bea951e9b025": {
      "workers": {
        "app/[[...slug]]/page": {
          "moduleId": 838458,
          "async": true,
          "exportedName": "getStockRepairsPreviewAction",
          "filename": "src/app/actions/inventory.ts"
        }
      },
      "layer": {
        "app/[[...slug]]/page": "action-browser"
      },
      "exportedName": "getStockRepairsPreviewAction",
      "filename": "src/app/actions/inventory.ts"
    },
    "60a33152b65e6ef5593ff2b5c1d0a77d09216fe7e5": {
      "workers": {
        "app/[[...slug]]/page": {
          "moduleId": 838458,
          "async": true,
          "exportedName": "repairStockChainsAction",
          "filename": "src/app/actions/inventory.ts"
        }
      },
      "layer": {
        "app/[[...slug]]/page": "action-browser"
      },
      "exportedName": "repairStockChainsAction",
      "filename": "src/app/actions/inventory.ts"
    },
    "4035262824370ccd2af8788671f3cc8435d165a93b": {
      "workers": {
        "app/[[...slug]]/page": {
          "moduleId": 838458,
          "async": true,
          "exportedName": "getActivityByEntityIdsAction",
          "filename": "src/app/actions/inventory.ts"
        }
      },
      "layer": {
        "app/[[...slug]]/page": "action-browser"
      },
      "exportedName": "getActivityByEntityIdsAction",
      "filename": "src/app/actions/inventory.ts"
    },
    "60eb8a3f21a0957ca35a2a3606c2b8e1d21977469d": {
      "workers": {
        "app/[[...slug]]/page": {
          "moduleId": 838458,
          "async": true,
          "exportedName": "updateStockHistoryDatesAction",
          "filename": "src/app/actions/inventory.ts"
        }
      },
      "layer": {
        "app/[[...slug]]/page": "action-browser"
      },
      "exportedName": "updateStockHistoryDatesAction",
      "filename": "src/app/actions/inventory.ts"
    },
    "40db42f6103f55b9f7ade5c65ca70a00feff7ff278": {
      "workers": {
        "app/[[...slug]]/page": {
          "moduleId": 838458,
          "async": true,
          "exportedName": "findCashTransactionAction",
          "filename": "src/app/actions/finance.ts"
        }
      },
      "layer": {
        "app/[[...slug]]/page": "action-browser"
      },
      "exportedName": "findCashTransactionAction",
      "filename": "src/app/actions/finance.ts"
    },
    "600b97f3c90242ca4be1574d304e260e5e07e3c8cf": {
      "workers": {
        "app/[[...slug]]/page": {
          "moduleId": 838458,
          "async": true,
          "exportedName": "getMessagesAction",
          "filename": "src/app/actions/messaging.ts"
        }
      },
      "layer": {
        "app/[[...slug]]/page": "action-browser"
      },
      "exportedName": "getMessagesAction",
      "filename": "src/app/actions/messaging.ts"
    },
    "40fae8e3cd20e274d8835c219996fbcfcdde06446f": {
      "workers": {
        "app/[[...slug]]/page": {
          "moduleId": 838458,
          "async": true,
          "exportedName": "createMessageAction",
          "filename": "src/app/actions/messaging.ts"
        }
      },
      "layer": {
        "app/[[...slug]]/page": "action-browser"
      },
      "exportedName": "createMessageAction",
      "filename": "src/app/actions/messaging.ts"
    },
    "608c56e751f1517abf78af3f8f4b1eb817c5efcecc": {
      "workers": {
        "app/[[...slug]]/page": {
          "moduleId": 838458,
          "async": true,
          "exportedName": "getMessageTemplatesAction",
          "filename": "src/app/actions/messaging.ts"
        }
      },
      "layer": {
        "app/[[...slug]]/page": "action-browser"
      },
      "exportedName": "getMessageTemplatesAction",
      "filename": "src/app/actions/messaging.ts"
    },
    "4012401c60d205ed481a496ad745ca64dfad82e200": {
      "workers": {
        "app/[[...slug]]/page": {
          "moduleId": 838458,
          "async": true,
          "exportedName": "createMessageTemplateAction",
          "filename": "src/app/actions/messaging.ts"
        }
      },
      "layer": {
        "app/[[...slug]]/page": "action-browser"
      },
      "exportedName": "createMessageTemplateAction",
      "filename": "src/app/actions/messaging.ts"
    },
    "60a4c2261958cabb4ed4ad155b1559b15bd9b1c7a3": {
      "workers": {
        "app/[[...slug]]/page": {
          "moduleId": 838458,
          "async": true,
          "exportedName": "updateMessageTemplateAction",
          "filename": "src/app/actions/messaging.ts"
        }
      },
      "layer": {
        "app/[[...slug]]/page": "action-browser"
      },
      "exportedName": "updateMessageTemplateAction",
      "filename": "src/app/actions/messaging.ts"
    },
    "406dfcb8705c888c32dc2bb1380b80464b3977c05d": {
      "workers": {
        "app/[[...slug]]/page": {
          "moduleId": 838458,
          "async": true,
          "exportedName": "deleteMessageTemplateAction",
          "filename": "src/app/actions/messaging.ts"
        }
      },
      "layer": {
        "app/[[...slug]]/page": "action-browser"
      },
      "exportedName": "deleteMessageTemplateAction",
      "filename": "src/app/actions/messaging.ts"
    },
    "707be093cac72269888b676c90752075900286c135": {
      "workers": {
        "app/[[...slug]]/page": {
          "moduleId": 838458,
          "async": true,
          "exportedName": "upsertSaleAction",
          "filename": "src/app/actions/sales.ts"
        }
      },
      "layer": {
        "app/[[...slug]]/page": "action-browser"
      },
      "exportedName": "upsertSaleAction",
      "filename": "src/app/actions/sales.ts"
    },
    "40696a4456c7690d29b12ef602356cbc9be3c34a97": {
      "workers": {
        "app/[[...slug]]/page": {
          "moduleId": 838458,
          "async": true,
          "exportedName": "getCustomerCategoriesAction",
          "filename": "src/app/actions/customers.ts"
        }
      },
      "layer": {
        "app/[[...slug]]/page": "action-browser"
      },
      "exportedName": "getCustomerCategoriesAction",
      "filename": "src/app/actions/customers.ts"
    },
    "70b04375c8b1e7a5a64b19d8153628c90f1150c267": {
      "workers": {
        "app/[[...slug]]/page": {
          "moduleId": 838458,
          "async": true,
          "exportedName": "createCustomerCategoryAction",
          "filename": "src/app/actions/customers.ts"
        }
      },
      "layer": {
        "app/[[...slug]]/page": "action-browser"
      },
      "exportedName": "createCustomerCategoryAction",
      "filename": "src/app/actions/customers.ts"
    },
    "605890db4ca201299b68a3100db491232317cf530d": {
      "workers": {
        "app/[[...slug]]/page": {
          "moduleId": 838458,
          "async": true,
          "exportedName": "updateCustomerCategoryAction",
          "filename": "src/app/actions/customers.ts"
        }
      },
      "layer": {
        "app/[[...slug]]/page": "action-browser"
      },
      "exportedName": "updateCustomerCategoryAction",
      "filename": "src/app/actions/customers.ts"
    },
    "4032dd367fa6b4bfc08062e47a1ca2ffb5e5eb04b0": {
      "workers": {
        "app/[[...slug]]/page": {
          "moduleId": 838458,
          "async": true,
          "exportedName": "deleteCustomerCategoryAction",
          "filename": "src/app/actions/customers.ts"
        }
      },
      "layer": {
        "app/[[...slug]]/page": "action-browser"
      },
      "exportedName": "deleteCustomerCategoryAction",
      "filename": "src/app/actions/customers.ts"
    },
    "403ecd539ba07dc1ae97e837a5af133a7339b5cb64": {
      "workers": {
        "app/[[...slug]]/page": {
          "moduleId": 838458,
          "async": true,
          "exportedName": "getExpensesAction",
          "filename": "src/app/actions/finance.ts"
        }
      },
      "layer": {
        "app/[[...slug]]/page": "action-browser"
      },
      "exportedName": "getExpensesAction",
      "filename": "src/app/actions/finance.ts"
    },
    "60ff4a4d37b8cdb46933c77d4c2feddf840c5c9e12": {
      "workers": {
        "app/[[...slug]]/page": {
          "moduleId": 838458,
          "async": true,
          "exportedName": "createExpenseAction",
          "filename": "src/app/actions/finance.ts"
        }
      },
      "layer": {
        "app/[[...slug]]/page": "action-browser"
      },
      "exportedName": "createExpenseAction",
      "filename": "src/app/actions/finance.ts"
    },
    "70d8f9fd83845cd0ba1effc4e3ccdba420d97bade6": {
      "workers": {
        "app/[[...slug]]/page": {
          "moduleId": 838458,
          "async": true,
          "exportedName": "updateExpenseAction",
          "filename": "src/app/actions/finance.ts"
        }
      },
      "layer": {
        "app/[[...slug]]/page": "action-browser"
      },
      "exportedName": "updateExpenseAction",
      "filename": "src/app/actions/finance.ts"
    },
    "40f5e1fa124fe3ebdec7f34b54a6837a1c32f5d22d": {
      "workers": {
        "app/[[...slug]]/page": {
          "moduleId": 838458,
          "async": true,
          "exportedName": "deleteExpenseAction",
          "filename": "src/app/actions/finance.ts"
        }
      },
      "layer": {
        "app/[[...slug]]/page": "action-browser"
      },
      "exportedName": "deleteExpenseAction",
      "filename": "src/app/actions/finance.ts"
    },
    "40a697434fd28c67d2c607c1f57f3439edf220a529": {
      "workers": {
        "app/[[...slug]]/page": {
          "moduleId": 838458,
          "async": true,
          "exportedName": "getExpenseCategoriesAction",
          "filename": "src/app/actions/finance.ts"
        }
      },
      "layer": {
        "app/[[...slug]]/page": "action-browser"
      },
      "exportedName": "getExpenseCategoriesAction",
      "filename": "src/app/actions/finance.ts"
    },
    "40127fd3ae724f72ea4406ee7bf136a2e88120db7f": {
      "workers": {
        "app/[[...slug]]/page": {
          "moduleId": 838458,
          "async": true,
          "exportedName": "createExpenseCategoryAction",
          "filename": "src/app/actions/finance.ts"
        }
      },
      "layer": {
        "app/[[...slug]]/page": "action-browser"
      },
      "exportedName": "createExpenseCategoryAction",
      "filename": "src/app/actions/finance.ts"
    },
    "408d7d1e536999dcf29cd979cf16838168c69252f0": {
      "workers": {
        "app/[[...slug]]/page": {
          "moduleId": 838458,
          "async": true,
          "exportedName": "deleteExpenseCategoryAction",
          "filename": "src/app/actions/finance.ts"
        }
      },
      "layer": {
        "app/[[...slug]]/page": "action-browser"
      },
      "exportedName": "deleteExpenseCategoryAction",
      "filename": "src/app/actions/finance.ts"
    },
    "7062b9fc92a24c208cfe0ff340b8c459971725aba8": {
      "workers": {
        "app/[[...slug]]/page": {
          "moduleId": 838458,
          "async": true,
          "exportedName": "createDefaultExpenseCategoriesAction",
          "filename": "src/app/actions/finance.ts"
        }
      },
      "layer": {
        "app/[[...slug]]/page": "action-browser"
      },
      "exportedName": "createDefaultExpenseCategoriesAction",
      "filename": "src/app/actions/finance.ts"
    },
    "4062f5167d8450401fb1c1894fd92a5d62fc63ab55": {
      "workers": {
        "app/[[...slug]]/page": {
          "moduleId": 838458,
          "async": true,
          "exportedName": "getCarriageInwardsAction",
          "filename": "src/app/actions/carriageInwards.ts"
        }
      },
      "layer": {
        "app/[[...slug]]/page": "action-browser"
      },
      "exportedName": "getCarriageInwardsAction",
      "filename": "src/app/actions/carriageInwards.ts"
    },
    "70092a7345137d042552225207b9c87626a83302fb": {
      "workers": {
        "app/[[...slug]]/page": {
          "moduleId": 838458,
          "async": true,
          "exportedName": "createCarriageInwardAction",
          "filename": "src/app/actions/carriageInwards.ts"
        }
      },
      "layer": {
        "app/[[...slug]]/page": "action-browser"
      },
      "exportedName": "createCarriageInwardAction",
      "filename": "src/app/actions/carriageInwards.ts"
    },
    "7098b1956be922b248aeaf6a1abbd5218f57924a7c": {
      "workers": {
        "app/[[...slug]]/page": {
          "moduleId": 838458,
          "async": true,
          "exportedName": "updateCarriageInwardAction",
          "filename": "src/app/actions/carriageInwards.ts"
        }
      },
      "layer": {
        "app/[[...slug]]/page": "action-browser"
      },
      "exportedName": "updateCarriageInwardAction",
      "filename": "src/app/actions/carriageInwards.ts"
    },
    "60d170a5cfe5bd35fcab0395360e5c1b90e317f15a": {
      "workers": {
        "app/[[...slug]]/page": {
          "moduleId": 838458,
          "async": true,
          "exportedName": "deleteCarriageInwardAction",
          "filename": "src/app/actions/carriageInwards.ts"
        }
      },
      "layer": {
        "app/[[...slug]]/page": "action-browser"
      },
      "exportedName": "deleteCarriageInwardAction",
      "filename": "src/app/actions/carriageInwards.ts"
    },
    "6034a5c363e12c48d78921a1e0770dbce94f6cff56": {
      "workers": {
        "app/[[...slug]]/page": {
          "moduleId": 838458,
          "async": true,
          "exportedName": "getTasksAction",
          "filename": "src/app/actions/tasks.ts"
        }
      },
      "layer": {
        "app/[[...slug]]/page": "action-browser"
      },
      "exportedName": "getTasksAction",
      "filename": "src/app/actions/tasks.ts"
    },
    "40a5a43b9d2632d76958b3c459aff9994a66bba2ac": {
      "workers": {
        "app/[[...slug]]/page": {
          "moduleId": 838458,
          "async": true,
          "exportedName": "createTaskAction",
          "filename": "src/app/actions/tasks.ts"
        }
      },
      "layer": {
        "app/[[...slug]]/page": "action-browser"
      },
      "exportedName": "createTaskAction",
      "filename": "src/app/actions/tasks.ts"
    },
    "70de349f8e2650f26ed27e9de63484d5cbd53d334e": {
      "workers": {
        "app/[[...slug]]/page": {
          "moduleId": 838458,
          "async": true,
          "exportedName": "updateTaskAction",
          "filename": "src/app/actions/tasks.ts"
        }
      },
      "layer": {
        "app/[[...slug]]/page": "action-browser"
      },
      "exportedName": "updateTaskAction",
      "filename": "src/app/actions/tasks.ts"
    },
    "60848e5dc2214628ecd58a67490456df40858e9cf4": {
      "workers": {
        "app/[[...slug]]/page": {
          "moduleId": 838458,
          "async": true,
          "exportedName": "deleteTaskAction",
          "filename": "src/app/actions/tasks.ts"
        }
      },
      "layer": {
        "app/[[...slug]]/page": "action-browser"
      },
      "exportedName": "deleteTaskAction",
      "filename": "src/app/actions/tasks.ts"
    },
    "70f1e5fff4c4c8952afc4201a1485d37ce36b64a37": {
      "workers": {
        "app/[[...slug]]/page": {
          "moduleId": 838458,
          "async": true,
          "exportedName": "bulkUpdateTasksAction",
          "filename": "src/app/actions/tasks.ts"
        }
      },
      "layer": {
        "app/[[...slug]]/page": "action-browser"
      },
      "exportedName": "bulkUpdateTasksAction",
      "filename": "src/app/actions/tasks.ts"
    },
    "60bb437c9068ace00a64c1d86874015981b81e317e": {
      "workers": {
        "app/[[...slug]]/page": {
          "moduleId": 838458,
          "async": true,
          "exportedName": "getTaskCategoriesAction",
          "filename": "src/app/actions/tasks.ts"
        }
      },
      "layer": {
        "app/[[...slug]]/page": "action-browser"
      },
      "exportedName": "getTaskCategoriesAction",
      "filename": "src/app/actions/tasks.ts"
    },
    "70ed67048c4c61e5594abf6f17318d25dd1920aa49": {
      "workers": {
        "app/[[...slug]]/page": {
          "moduleId": 838458,
          "async": true,
          "exportedName": "createTaskCategoryAction",
          "filename": "src/app/actions/tasks.ts"
        }
      },
      "layer": {
        "app/[[...slug]]/page": "action-browser"
      },
      "exportedName": "createTaskCategoryAction",
      "filename": "src/app/actions/tasks.ts"
    },
    "7030b3a2027f25d11b3e1649f9f48de595689e998d": {
      "workers": {
        "app/[[...slug]]/page": {
          "moduleId": 838458,
          "async": true,
          "exportedName": "updateTaskCategoryAction",
          "filename": "src/app/actions/tasks.ts"
        }
      },
      "layer": {
        "app/[[...slug]]/page": "action-browser"
      },
      "exportedName": "updateTaskCategoryAction",
      "filename": "src/app/actions/tasks.ts"
    },
    "6046a2f8db1a44bfb779f4ccf2c1c8815918bdf60e": {
      "workers": {
        "app/[[...slug]]/page": {
          "moduleId": 838458,
          "async": true,
          "exportedName": "deleteTaskCategoryAction",
          "filename": "src/app/actions/tasks.ts"
        }
      },
      "layer": {
        "app/[[...slug]]/page": "action-browser"
      },
      "exportedName": "deleteTaskCategoryAction",
      "filename": "src/app/actions/tasks.ts"
    },
    "60f0a493b50e7389723a1c99f08bf7a82512acceff": {
      "workers": {
        "app/[[...slug]]/page": {
          "moduleId": 838458,
          "async": true,
          "exportedName": "createDefaultTaskCategoriesAction",
          "filename": "src/app/actions/tasks.ts"
        }
      },
      "layer": {
        "app/[[...slug]]/page": "action-browser"
      },
      "exportedName": "createDefaultTaskCategoriesAction",
      "filename": "src/app/actions/tasks.ts"
    }
  },
  "edge": {}
}